xdist_scheduling_exclusive/__about__.py
xdist_scheduling_exclusive/__init__.py
xdist_scheduling_exclusive/exclusive_load_scheduling.py
xdist_scheduling_exclusive/exclusive_loadfile_scheduling.py
xdist_scheduling_exclusive/exclusive_loadscope_scheduling.py
xdist_scheduling_exclusive/scheduler_base.py
xdist_scheduling_exclusive-1.2.0.dist-info/METADATA
xdist_scheduling_exclusive-1.2.0.dist-info/WHEEL
xdist_scheduling_exclusive-1.2.0.dist-info/licenses/LICENSE.txt
xdist_scheduling_exclusive-1.2.0.dist-info/RECORD
