Metadata-Version: 2.1
Name: xdist-scheduling-exclusive
Version: 1.2.0
Summary: pytest-xdist scheduler that runs some tests on dedicated workers. can significantly improve runtime by running long tests on separate workers.
Project-URL: Homepage, https://andgineer.github.io/xdist-scheduling-exclusive/
Project-URL: Documentation, https://andgineer.github.io/xdist-scheduling-exclusive/
Author-email: Andrey Sorokin <andrey@sorokin.engineer>
License: Copyright (c) 2021 Andrey Sorokin <andrey@sorokin.engineer>
License-File: LICENSE.txt
Keywords: log,log-handler,opensearch
Classifier: License :: OSI Approved :: MIT License
Classifier: Operating System :: OS Independent
Classifier: Programming Language :: Python :: 3
Requires-Python: >=3.9
Requires-Dist: pytest-xdist
